pypoai.py
pypoai-1.0.dist-info/METADATA
pypoai-1.0.dist-info/WHEEL
pypoai-1.0.dist-info/top_level.txt
pypoai-1.0.dist-info/RECORD
