Metadata-Version: 2.4
Name: pypoai
Version: 1.0
Summary: poai: A comprehensive tool for Gettext PO (.po) translation files. It automates translations using artificial intelligence and provides seamless bidirectional conversion between PO and JSON formats.
Home-page: https://github.com/hasancagrigungor/poai
Author: Hasan Çağrı Güngör
Author-email: iletisim@cagrigungor.com
License: MIT
Keywords: .po translate,po to json,json to po
Classifier: License :: OSI Approved :: MIT License
Classifier: Programming Language :: Python :: 3
Classifier: Programming Language :: Python :: 3.6
Classifier: Programming Language :: Python :: 3.7
Classifier: Programming Language :: Python :: 3.8
Classifier: Programming Language :: Python :: 3.9
Classifier: Programming Language :: Python :: 3.10
Classifier: Programming Language :: Python :: 3.11
Classifier: Programming Language :: Python :: 3.12
Classifier: Programming Language :: Python :: 3.13
Dynamic: author
Dynamic: author-email
Dynamic: classifier
Dynamic: description
Dynamic: description-content-type
Dynamic: home-page
Dynamic: keywords
Dynamic: license
Dynamic: summary
